bioemu/__init__.py
bioemu/chemgraph.py
bioemu/convert_chemgraph.py
bioemu/denoiser.py
bioemu/get_embeds.py
bioemu/md_utils.py
bioemu/model_utils.py
bioemu/models.py
bioemu/run_hpacker.py
bioemu/sample.py
bioemu/sde_lib.py
bioemu/seq_io.py
bioemu/shortcuts.py
bioemu/sidechain_relax.py
bioemu/so3_sde.py
bioemu/structure_module.py
bioemu/utils.py
bioemu/colabfold_setup/__init__.py
bioemu/colabfold_setup/batch.patch
bioemu/colabfold_setup/modules.patch
bioemu/colabfold_setup/setup.sh
bioemu/config/denoiser/dpm.yaml
bioemu/config/denoiser/heun.yaml
bioemu/hpacker_setup/__init__.py
bioemu/hpacker_setup/setup_hpacker.py
bioemu/hpacker_setup/setup_sidechain_relax.sh
bioemu/openfold/np/protein.py
bioemu/openfold/np/residue_constants.py
bioemu/openfold/utils/rigid_utils.py
bioemu/training/foldedness.py
bioemu/training/loss.py
bioemu-1.1.0.dist-info/licenses/LICENSE
bioemu-1.1.0.dist-info/licenses/NOTICE.md
bioemu-1.1.0.dist-info/METADATA
bioemu-1.1.0.dist-info/WHEEL
bioemu-1.1.0.dist-info/top_level.txt
bioemu-1.1.0.dist-info/RECORD
