Metadata-Version: 2.4
Name: bioemu
Version: 1.1.0
Summary: Biomolecular emulator
Requires-Python: >=3.10
License-File: LICENSE
License-File: NOTICE.md
Requires-Dist: mdtraj>=1.9.9
Requires-Dist: torch_geometric>=2.6.1
Requires-Dist: torch>=2.6.0
Requires-Dist: modelcif==0.7
Requires-Dist: bio>=1.5.9
Requires-Dist: fire==0.7.0
Requires-Dist: huggingface-hub
Requires-Dist: hydra-core
Requires-Dist: dm-tree
Requires-Dist: stackprinter
Requires-Dist: typer
Requires-Dist: uv
Provides-Extra: dev
Requires-Dist: pytest; extra == "dev"
Requires-Dist: pytest-cov; extra == "dev"
Requires-Dist: pre-commit; extra == "dev"
Provides-Extra: md
Requires-Dist: openmm[cuda12]==8.2.0; extra == "md"
Dynamic: license-file
